fastapi_tarpit/__init__.py
fastapi_tarpit/client.py
fastapi_tarpit/config.py
fastapi_tarpit/middleware.py
fastapi_tarpit-1.0.4.dist-info/LICENSE
fastapi_tarpit-1.0.4.dist-info/METADATA
fastapi_tarpit-1.0.4.dist-info/WHEEL
fastapi_tarpit-1.0.4.dist-info/top_level.txt
fastapi_tarpit-1.0.4.dist-info/RECORD
