Metadata-Version: 2.1
Name: fastapi-tarpit
Version: 1.0.4
Summary: FastAPI middleware that purposely delays incoming connections on unused routes
Author-email: Mats Klepsland <mats.klepsland@gmail.com>
Project-URL: Homepage, https://github.com/thus/fastapi-tarpit
Project-URL: Issues, https://github.com/thus/fastapi-tarpit/issues
Classifier: Programming Language :: Python :: 3
Classifier: Framework :: FastAPI
Classifier: License :: OSI Approved :: MIT License
Classifier: Operating System :: OS Independent
Requires-Python: >=3.10
License-File: LICENSE
Requires-Dist: fastapi
